FastRoot-1.5.data/scripts/FastRoot.py
FastRoot-1.5.data/scripts/FastRoot_tests.py
FastRoot-1.5.data/scripts/compute_RTT.py
FastRoot-1.5.data/scripts/compute_variance.py
fastroot/LabelTree.py
fastroot/MinVar.py
fastroot/RTT.py
fastroot/Tree_extend.py
fastroot/__init__.py
fastroot/quadprog_solvers.py
fastroot/reroot_at_edge.py
fastroot/__pycache__/__init__.cpython-38.pyc
fastroot_tests/__init__.py
fastroot_tests/unit_test_MP_MV_OG.py
fastroot_tests/unit_test_RTT.py
fastroot_tests/utils.py
fastroot_tests/__pycache__/__init__.cpython-38.pyc
fastroot_tests/__pycache__/unit_test_MP_MV_OG.cpython-38.pyc
fastroot_tests/__pycache__/unit_test_RTT.cpython-38.pyc
fastroot_tests/__pycache__/utils.cpython-38.pyc
fastroot_tests/unit_test/MP/branches.txt
fastroot_tests/unit_test/MP/input.trees
fastroot_tests/unit_test/MP/output.trees
fastroot_tests/unit_test/MP/score.txt
fastroot_tests/unit_test/MP/special/branches.txt
fastroot_tests/unit_test/MP/special/input.trees
fastroot_tests/unit_test/MP/special/output.trees
fastroot_tests/unit_test/MP/special/score.txt
fastroot_tests/unit_test/MV/branches.txt
fastroot_tests/unit_test/MV/input.trees
fastroot_tests/unit_test/MV/output.trees
fastroot_tests/unit_test/MV/score.txt
fastroot_tests/unit_test/MV/special/branches.txt
fastroot_tests/unit_test/MV/special/input.trees
fastroot_tests/unit_test/MV/special/output.trees
fastroot_tests/unit_test/MV/special/score.txt
fastroot_tests/unit_test/OG/branches.txt
fastroot_tests/unit_test/OG/input.trees
fastroot_tests/unit_test/OG/outgroups.txt
fastroot_tests/unit_test/OG/output.trees
fastroot_tests/unit_test/OG/score.txt
fastroot_tests/unit_test/RTT/random_trees/input.trees
fastroot_tests/unit_test/RTT/random_trees/output.trees
fastroot_tests/unit_test/RTT/random_trees/sampling_times.txt
fastroot_tests/unit_test/RTT/random_trees/score.txt
fastroot_tests/unit_test/RTT/random_trees/100/input.tre
fastroot_tests/unit_test/RTT/random_trees/100/sampling_times.txt
FastRoot-1.5.dist-info/LICENSE
FastRoot-1.5.dist-info/METADATA
FastRoot-1.5.dist-info/WHEEL
FastRoot-1.5.dist-info/top_level.txt
FastRoot-1.5.dist-info/zip-safe
FastRoot-1.5.dist-info/RECORD
