Metadata-Version: 2.1
Name: FastRoot
Version: 1.5
Summary: UNKNOWN
Home-page: UNKNOWN
Author: ['Uyen Mai', 'Merve Kilic', 'Erfan Sayyari', 'Siavash Mirarab']
Author-email: UNKNOWN
License: MIT License
Keywords: Phylogenetics Evolution Biology
Platform: UNKNOWN
Classifier: Environment :: Console
Classifier: Intended Audience :: Developers
Classifier: Intended Audience :: Science/Research
Classifier: Natural Language :: English
Classifier: Operating System :: OS Independent
Classifier: Programming Language :: Python
Classifier: Topic :: Scientific/Engineering :: Bio-Informatics
Requires-Dist: treeswift (>=1.1.14)
Requires-Dist: cvxopt (>=1.2.5)
Requires-Dist: numpy (>=1.19.0)
